{"bseNseJson":[{"dateTime":"09:33 | 10-03-2021","etSymbol":"elpm","bestSellPrice":"201.80","listingFlag":true,"symbol":"ELGIEQUIP","preMarket":false,"trend":"equal","companyName":"Elgi Equipments","openPrice":"205.25","sectorRank":"2","instrument":"Equity","industry":"Compressors","bestBuyQty":"111","companyName2":"Elgi Equipments Ltd.","seoName":"elgi-equipments-ltd","fiftyTwoWeekHighDateTime":"Mar  9 2021  4:00PM","companyRankYear":"2020","fiftyTwoWeekHighPrice":"211.50","lowPrice":"198.05","segment":"BSE","highPrice":"206.05","scripCode":"522074","exchangeGroup":"A","lastTradedPrice":"201.45","sector":"Electric/Electronics","value":"0.12","netChange":"-2.95","percentChange":"-1.44","displayDateTime":"2021-03-10 09:33:00","companyType":"equity","tpilCode":"1124","bestSellQty":"8","volume":"5968","companyId":"13805","groupName":"A ","fiftyTwoWeekLowDateTime":"Apr  7 2020  4:00PM","faceValue":"1.00","companyRank":"NA","fiftyTwoWeekLowPrice":"51.12","nseScripCode":"ELGIEQUIP","closePrice":"204.40","isSME":false,"bestBuyPrice":"201.25","isinCode":"INE285A01027"},{"dateTime":"09:33 | 10-03-2021","etSymbol":"elgequ","bestSellPrice":"201.95","listingFlag":true,"symbol":"ELGIEQUIP","preMarket":false,"trend":"equal","companyName":"Elgi Equipments","openPrice":"205.90","sectorRank":"2","instrument":"Equity","industry":"Compressors","bestBuyQty":"52","companyName2":"Elgi Equipments Ltd.","seoName":"elgi-equipments-ltd","fiftyTwoWeekHighDateTime":"Mar  9 2021  3:59PM","companyRankYear":"2020","fiftyTwoWeekHighPrice":"211.60","lowPrice":"198.20","segment":"NSE","highPrice":"206.70","scripCode":"522074","exchangeGroup":"OtherEQ","lastTradedPrice":"201.80","sector":"Electric/Electronics","value":"1.57","netChange":"-2.70","percentChange":"-1.32","displayDateTime":"2021-03-10 09:33:00","companyType":"equity","tpilCode":"1124","bestSellQty":"15","volume":"77711","companyId":"13805","fiftyTwoWeekLowDateTime":"Apr  7 2020  3:58PM","faceValue":"1.00","wightedAverage":"202.08","companyRank":"NA","fiftyTwoWeekLowPrice":"50.60","nseScripCode":"ELGIEQUIPEQ","closePrice":"204.50","isSME":false,"bestBuyPrice":"201.55","isinCode":"INE285A01027"}],"companySD":[{"securitySubTypeId":"4","companyType":"equity","companyName":"Elgi Equipments Ltd.","year3sd":"2.1997","exchangeId":"50","companyId":"13805","year1sd":"2.4065","securityTypeId":"5","modified":"2020-06-23 11:01:00.0","month1sd":"2.4960","id":"10758","month6sd":"3.0533","month3sd":"2.8658"},{"securitySubTypeId":"4","companyType":"equity","companyName":"Elgi Equipments Ltd.","year3sd":"2.2343","exchangeId":"47","companyId":"13805","year1sd":"2.4839","securityTypeId":"5","modified":"2020-06-23 11:01:00.0","month1sd":"2.6283","id":"10757","month6sd":"3.1617","month3sd":"2.8910"}],"averageVolume":{"NSE":{"exchangeId":"50","companyid":"13805","fiveDaysAverage":"774582.0000","tenDaysAverage":"599156.2000","oneMonthAverage":"316495.0333"},"BSE":{"exchangeId":"47","companyid":"13805","fiveDaysAverage":"28866.8000","tenDaysAverage":"30500.1000","oneMonthAverage":"26212.8000"}},"companyBeta":[{"exchangeId":"47","companyId":"13805","oneYearBeta":"0.7622","companyType":"equity","sixMonthBeta":"0.5243","companyName":"Elgi Equipments Ltd.","threeMonthBeta":"0.6493","dateModified":"2019-08-20 01:15:44.0","threeYearBeta":"0.9920","oneMonthBeta":"1.4421"},{"exchangeId":"50","companyId":"13805","oneYearBeta":"0.6610","companyType":"equity","sixMonthBeta":"0.4630","companyName":"Elgi Equipments Ltd.","threeMonthBeta":"0.5008","dateModified":"2019-08-20 01:15:44.0","threeYearBeta":"0.9033","oneMonthBeta":"1.0965"}]}
