{"bseNseJson":[{"dateTime":"16:00 | 27-01-2021","etSymbol":"fidu","bestSellPrice":"0","listingFlag":true,"symbol":"FINOLEXIND","preMarket":false,"trend":"equal","companyName":"Finolex Industries","openPrice":"580.05","sectorRank":"3","instrument":"Equity","industry":"Plastics - Pipes & Fittings","bestBuyQty":"0","companyName2":"Finolex Industries Ltd.","seoName":"finolex-industries-ltd","fiftyTwoWeekHighDateTime":"Jan 11 2021  4:00PM","companyRankYear":"2020","fiftyTwoWeekHighPrice":"675.00","lowPrice":"580.05","segment":"BSE","highPrice":"607.55","scripCode":"500940","exchangeGroup":"A","sector":"Plastics","lastTradedPrice":"589.15","value":"0.23","netChange":"6.70","percentChange":"1.15","displayDateTime":"2021-01-27 16:00:00","companyType":"equity","tpilCode":"1260","bestSellQty":"0","volume":"3837","companyId":"13760","groupName":"A ","fiftyTwoWeekLowDateTime":"Mar 24 2020  4:00PM","faceValue":"10.00","companyRank":"380","nseScripCode":"FINPIPE","fiftyTwoWeekLowPrice":"283.00","closePrice":"582.45","isSME":false,"bestBuyPrice":"0","isinCode":"INE183A01016"},{"dateTime":"15:53 | 27-01-2021","etSymbol":"finind","bestSellPrice":"0","listingFlag":true,"symbol":"FINPIPE","preMarket":false,"trend":"equal","companyName":"Finolex Industries","openPrice":"585.70","sectorRank":"3","instrument":"Equity","industry":"Plastics - Pipes & Fittings","bestBuyQty":"0","companyName2":"Finolex Industries Ltd.","seoName":"finolex-industries-ltd","fiftyTwoWeekHighDateTime":"Jan  8 2021  3:54PM","companyRankYear":"2020","fiftyTwoWeekHighPrice":"673.50","lowPrice":"580.15","segment":"NSE","highPrice":"608.00","scripCode":"500940","exchangeGroup":"OtherEQ","sector":"Plastics","lastTradedPrice":"589.90","value":"6.61","netChange":"7.00","percentChange":"1.20","displayDateTime":"2021-01-27 15:53:00","companyType":"equity","tpilCode":"1260","bestSellQty":"0","volume":"111323","companyId":"13760","fiftyTwoWeekLowDateTime":"Mar 24 2020  3:59PM","faceValue":"10.00","wightedAverage":"593.90","companyRank":"380","nseScripCode":"FINPIPEEQ","fiftyTwoWeekLowPrice":"289.95","closePrice":"582.90","isSME":false,"bestBuyPrice":"0","isinCode":"INE183A01016"}],"companySD":[{"companyType":"equity","securitySubTypeId":"4","companyName":"Finolex Industries Ltd.","year3sd":"2.1609","exchangeId":"50","companyId":"13760","year1sd":"2.9616","securityTypeId":"5","month1sd":"3.1225","modified":"2020-06-23 11:01:14.0","id":"10720","month6sd":"3.8269","month3sd":"3.7935"},{"companyType":"equity","securitySubTypeId":"4","companyName":"Finolex Industries Ltd.","year3sd":"2.1220","exchangeId":"47","companyId":"13760","year1sd":"2.9060","securityTypeId":"5","month1sd":"3.4326","modified":"2020-06-23 11:01:14.0","id":"10719","month6sd":"3.7909","month3sd":"3.8878"}],"averageVolume":{"NSE":{"exchangeId":"50","companyid":"13760","fiveDaysAverage":"108019.2000","tenDaysAverage":"77677.4000","oneMonthAverage":"89353.2667"},"BSE":{"exchangeId":"47","companyid":"13760","fiveDaysAverage":"6562.8000","tenDaysAverage":"7097.1000","oneMonthAverage":"10599.6667"}},"companyBeta":[{"exchangeId":"47","oneYearBeta":"0.7470","companyId":"13760","companyType":"equity","sixMonthBeta":"0.8701","companyName":"Finolex Industries Ltd.","threeMonthBeta":"0.9693","dateModified":"2019-08-20 01:16:19.0","threeYearBeta":"0.7359","oneMonthBeta":"1.2220"},{"exchangeId":"50","oneYearBeta":"0.7493","companyId":"13760","companyType":"equity","sixMonthBeta":"0.9592","companyName":"Finolex Industries Ltd.","threeMonthBeta":"1.0562","dateModified":"2019-08-20 01:16:19.0","threeYearBeta":"0.7146","oneMonthBeta":"1.2800"}]}
