{"chart":{"result":[{"meta":{"currency":"INR","symbol":"HERITGFOOD.NS","exchangeName":"NSI","instrumentType":"EQUITY","firstTradeDate":1025495100,"regularMarketTime":1610430541,"gmtoffset":19800,"timezone":"IST","exchangeTimezoneName":"Asia/Kolkata","regularMarketPrice":312.0,"chartPreviousClose":307.9,"priceHint":2,"currentTradingPeriod":{"pre":{"timezone":"IST","start":1610423100,"end":1610423100,"gmtoffset":19800},"regular":{"timezone":"IST","start":1610423100,"end":1610445600,"gmtoffset":19800},"post":{"timezone":"IST","start":1610445600,"end":1610445600,"gmtoffset":19800}},"dataGranularity":"1d","range":"1d","validRanges":["1d","5d","1mo","3mo","6mo","1y","2y","5y","10y","ytd","max"]},"timestamp":[1610430541],"indicators":{"quote":[{"high":[320.0],"close":[312.0],"low":[305.0],"open":[309.45001220703125],"volume":[102305]}],"adjclose":[{"adjclose":[312.0]}]}}],"error":null}}