{"bseNseJson":[{"dateTime":"16:00 | 17-05-2021","etSymbol":"manore","bestSellPrice":"0","listingFlag":true,"symbol":"MOIL","preMarket":false,"trend":"equal","companyName":"MOIL","openPrice":"181.95","sectorRank":"4","industry":"Mining/Minerals","instrument":"Equity","bestBuyQty":"0","companyName2":"MOIL Ltd.","seoName":"moil-ltd","fiftyTwoWeekHighDateTime":"May 12 2021  4:00PM","companyRankYear":"2020","fiftyTwoWeekHighPrice":"195.95","lowPrice":"175.35","segment":"BSE","highPrice":"183.90","scripCode":"533286","exchangeGroup":"A","sector":"Mining","lastTradedPrice":"179.60","value":"5.26","netChange":"2.50","percentChange":"1.41","displayDateTime":"2021-05-17 16:00:00","companyType":"equity","tpilCode":"7025","bestSellQty":"0","volume":"292274","companyId":"4501","groupName":"A ","fiftyTwoWeekLowDateTime":"Nov 14 2020  7:35PM","faceValue":"10.00","companyRank":"NA","fiftyTwoWeekLowPrice":"119.00","nseScripCode":"MOIL","closePrice":"177.10","isSME":false,"bestBuyPrice":"0","isinCode":"INE490G01020"},{"dateTime":"15:58 | 17-05-2021","etSymbol":"manore","bestSellPrice":"0","listingFlag":true,"symbol":"MOIL","preMarket":false,"trend":"equal","companyName":"MOIL","openPrice":"179.70","sectorRank":"4","industry":"Mining/Minerals","instrument":"Equity","bestBuyQty":"0","companyName2":"MOIL Ltd.","seoName":"moil-ltd","fiftyTwoWeekHighDateTime":"May 12 2021  4:00PM","companyRankYear":"2020","fiftyTwoWeekHighPrice":"196.00","lowPrice":"175.10","segment":"NSE","highPrice":"184.00","scripCode":"533286","exchangeGroup":"OtherEQ","sector":"Mining","lastTradedPrice":"180.00","value":"38.49","netChange":"2.65","percentChange":"1.49","displayDateTime":"2021-05-17 15:58:00","companyType":"equity","tpilCode":"7025","bestSellQty":"0","volume":"2143885","companyId":"4501","fiftyTwoWeekLowDateTime":"May 20 2020  3:54PM","faceValue":"10.00","wightedAverage":"179.55","companyRank":"NA","fiftyTwoWeekLowPrice":"120.30","nseScripCode":"MOILEQ","closePrice":"177.35","isSME":false,"bestBuyPrice":"0","isinCode":"INE490G01020"}],"companySD":[{"companyType":"equity","securitySubTypeId":"4","companyName":"MOIL Ltd.","exchangeId":"50","year3sd":"2.3886","companyId":"4501","year1sd":"2.9099","securityTypeId":"5","month1sd":"3.7964","modified":"2020-06-23 11:03:57.0","id":"7354","month6sd":"3.6252","month3sd":"4.0903"},{"companyType":"equity","securitySubTypeId":"4","companyName":"MOIL Ltd.","exchangeId":"47","year3sd":"2.3705","companyId":"4501","year1sd":"2.9178","securityTypeId":"5","month1sd":"3.9267","modified":"2020-06-23 11:03:56.0","id":"7353","month6sd":"3.6959","month3sd":"4.2188"}],"averageVolume":{"NSE":{"exchangeId":"50","companyid":"4501","fiveDaysAverage":"4627061.6000","tenDaysAverage":"3057450.6000","oneMonthAverage":"1706581.3000"},"BSE":{"exchangeId":"47","companyid":"4501","fiveDaysAverage":"364647.6000","tenDaysAverage":"244117.1000","oneMonthAverage":"138090.6333"}},"companyBeta":[{"exchangeId":"47","companyId":"4501","oneYearBeta":"0.8640","companyType":"equity","sixMonthBeta":"1.0274","companyName":"MOIL Ltd.","threeMonthBeta":"0.8638","dateModified":"2019-08-20 01:23:06.0","threeYearBeta":"1.1627","oneMonthBeta":"0.9197"},{"exchangeId":"50","companyId":"4501","oneYearBeta":"0.8531","companyType":"equity","sixMonthBeta":"1.0298","companyName":"MOIL Ltd.","threeMonthBeta":"0.9072","dateModified":"2019-08-20 01:23:06.0","threeYearBeta":"1.1779","oneMonthBeta":"1.0480"}]}
