{"bseNseJson":[{"dateTime":"16:00 | 27-01-2021","etSymbol":"newind","bestSellPrice":"0","listingFlag":true,"symbol":"NIACL","preMarket":false,"trend":"equal","companyName":"New Indian Assurance","openPrice":"127.40","sectorRank":"9","instrument":"Equity","industry":"Insurance - Non Life","bestBuyQty":"0","companyName2":"The New India Assurance Company Ltd.","seoName":"the-new-india-assurance-company-ltd","fiftyTwoWeekHighDateTime":"Jan 27 2020  4:00PM","companyRankYear":"2020","fiftyTwoWeekHighPrice":"167.30","lowPrice":"127.40","segment":"BSE","highPrice":"131.00","scripCode":"540769","exchangeGroup":"A","sector":"Financial Services","lastTradedPrice":"129.20","value":"0.28","netChange":"1.80","percentChange":"1.41","displayDateTime":"2021-01-27 16:00:00","companyType":"equity","tpilCode":"5797","bestSellQty":"0","volume":"21696","companyId":"4285","groupName":"A ","fiftyTwoWeekLowDateTime":"Mar 24 2020  4:00PM","faceValue":"5.00","companyRank":"61","fiftyTwoWeekLowPrice":"75.00","nseScripCode":"NIACL","closePrice":"127.40","isSME":false,"bestBuyPrice":"0","isinCode":"INE470Y01017"},{"dateTime":"15:59 | 27-01-2021","etSymbol":"newind","bestSellPrice":"0","listingFlag":true,"symbol":"NIACL","preMarket":false,"trend":"equal","companyName":"New Indian Assurance","openPrice":"128.00","sectorRank":"9","instrument":"Equity","industry":"Insurance - Non Life","bestBuyQty":"0","companyName2":"The New India Assurance Company Ltd.","seoName":"the-new-india-assurance-company-ltd","fiftyTwoWeekHighDateTime":"Jan 27 2020  3:59PM","companyRankYear":"2020","fiftyTwoWeekHighPrice":"167.35","lowPrice":"127.20","segment":"NSE","highPrice":"131.25","scripCode":"540769","exchangeGroup":"OtherEQ","sector":"Financial Services","lastTradedPrice":"129.25","value":"4.44","netChange":"1.75","percentChange":"1.37","displayDateTime":"2021-01-27 15:59:00","companyType":"equity","tpilCode":"5797","bestSellQty":"0","volume":"342395","companyId":"4285","fiftyTwoWeekLowDateTime":"Mar 13 2020  4:01PM","faceValue":"5.00","wightedAverage":"129.53","companyRank":"61","fiftyTwoWeekLowPrice":"74.10","nseScripCode":"NIACLEQ","closePrice":"127.50","isSME":false,"bestBuyPrice":"0","isinCode":"INE470Y01017"}],"companySD":[{"exchangeId":"50","companyId":"4285","year1sd":"3.8772","securityTypeId":"5","securitySubTypeId":"4","companyType":"equity","companyName":"The New India Assurance Company Ltd.","month1sd":"2.7077","modified":"2020-06-23 11:06:49.0","id":"12668","month6sd":"4.0386","month3sd":"4.1663"},{"exchangeId":"47","companyId":"4285","year1sd":"3.9818","securityTypeId":"5","securitySubTypeId":"4","companyType":"equity","companyName":"The New India Assurance Company Ltd.","month1sd":"1.9000","modified":"2020-06-23 11:06:49.0","id":"12669","month6sd":"4.1365","month3sd":"4.0730"}],"averageVolume":{"NSE":{"exchangeId":"50","companyid":"4285","fiveDaysAverage":"1566984.2000","tenDaysAverage":"1014206.6000","oneMonthAverage":"867696.6333"},"BSE":{"exchangeId":"47","companyid":"4285","fiveDaysAverage":"107393.6000","tenDaysAverage":"78737.5000","oneMonthAverage":"60949.4000"}},"companyBeta":[{"exchangeId":"47","companyId":"4285","oneYearBeta":"0.6606","companyType":"equity","sixMonthBeta":"0.7707","companyName":"The New India Assurance Company Ltd.","threeMonthBeta":"0.5913","dateModified":"2019-08-20 01:30:51.0","oneMonthBeta":"0.9657"},{"exchangeId":"50","companyId":"4285","oneYearBeta":"0.5841","companyType":"equity","sixMonthBeta":"0.7097","companyName":"The New India Assurance Company Ltd.","threeMonthBeta":"0.5726","dateModified":"2019-08-20 01:30:51.0","oneMonthBeta":"1.0828"}]}
