{"bseNseJson":[{"etSymbol":"rils","dateTime":"09:32 | 10-03-2021","listingFlag":true,"bestSellPrice":"267.55","symbol":"RALLIS","preMarket":false,"trend":"equal","companyName":"Rallis India","sectorRank":"5","openPrice":"269.10","industry":"Pesticides/Agro Chem","instrument":"Equity","bestBuyQty":"36","companyName2":"Rallis India Ltd.","seoName":"rallis-india-ltd","companyRankYear":"2020","fiftyTwoWeekHighDateTime":"Aug 26 2020  4:00PM","fiftyTwoWeekHighPrice":"340.00","lowPrice":"266.80","segment":"BSE","highPrice":"270.75","scripCode":"500355","exchangeGroup":"A","lastTradedPrice":"267.50","sector":"Pesticides/Agro Chemicals","value":"0.09","netChange":"-1.60","percentChange":"-0.59","displayDateTime":"2021-03-10 09:32:00","companyType":"equity","tpilCode":"3361","bestSellQty":"36","volume":"3357","companyId":"13204","groupName":"A ","fiftyTwoWeekLowDateTime":"Mar 24 2020  4:00PM","faceValue":"1.00","companyRank":"472","nseScripCode":"RALLIS","fiftyTwoWeekLowPrice":"127.10","closePrice":"269.10","isSME":false,"bestBuyPrice":"266.85","isinCode":"INE613A01020"},{"etSymbol":"ralind","dateTime":"09:32 | 10-03-2021","listingFlag":true,"bestSellPrice":"267.25","symbol":"RALLIS","preMarket":false,"trend":"equal","companyName":"Rallis India","sectorRank":"5","openPrice":"269.35","industry":"Pesticides/Agro Chem","instrument":"Equity","bestBuyQty":"145","companyName2":"Rallis India Ltd.","seoName":"rallis-india-ltd","companyRankYear":"2020","fiftyTwoWeekHighDateTime":"Aug 26 2020  3:59PM","fiftyTwoWeekHighPrice":"339.80","lowPrice":"266.60","segment":"NSE","highPrice":"270.90","scripCode":"400355","exchangeGroup":"OtherEQ","lastTradedPrice":"267.05","sector":"Pesticides/Agro Chemicals","value":"1.48","netChange":"-1.50","percentChange":"-0.56","displayDateTime":"2021-03-10 09:32:00","companyType":"equity","tpilCode":"3361","bestSellQty":"1","volume":"54991","companyId":"13204","fiftyTwoWeekLowDateTime":"Mar 24 2020  3:59PM","faceValue":"1.00","wightedAverage":"269.00","companyRank":"472","nseScripCode":"RALLISEQ","fiftyTwoWeekLowPrice":"125.00","closePrice":"268.55","isSME":false,"bestBuyPrice":"266.95","isinCode":"INE613A01020"}],"companySD":[{"companyType":"equity","securitySubTypeId":"4","companyName":"Rallis India Ltd.","exchangeId":"50","year3sd":"2.2813","companyId":"13204","year1sd":"3.0604","securityTypeId":"5","month1sd":"2.9902","modified":"2020-06-23 11:05:02.0","id":"10303","month6sd":"3.9314","month3sd":"3.5588"},{"companyType":"equity","securitySubTypeId":"4","companyName":"Rallis India Ltd.","exchangeId":"47","year3sd":"2.2453","companyId":"13204","year1sd":"3.0285","securityTypeId":"5","month1sd":"3.1908","modified":"2020-06-23 11:05:02.0","id":"10302","month6sd":"3.9307","month3sd":"3.5760"}],"averageVolume":{"NSE":{"exchangeId":"50","companyid":"13204","fiveDaysAverage":"1918841.8000","tenDaysAverage":"1232089.4000","oneMonthAverage":"661630.6667"},"BSE":{"exchangeId":"47","companyid":"13204","fiveDaysAverage":"135389.0000","tenDaysAverage":"91648.5000","oneMonthAverage":"54061.7333"}},"companyBeta":[{"exchangeId":"47","companyId":"13204","oneYearBeta":"0.6498","companyType":"equity","sixMonthBeta":"0.6209","companyName":"Rallis India Ltd.","threeMonthBeta":"0.5332","dateModified":"2019-08-20 01:26:22.0","threeYearBeta":"0.8395","oneMonthBeta":"0.2171"},{"exchangeId":"50","companyId":"13204","oneYearBeta":"0.6002","companyType":"equity","sixMonthBeta":"0.5277","companyName":"Rallis India Ltd.","threeMonthBeta":"0.4647","dateModified":"2019-08-20 01:26:22.0","threeYearBeta":"0.8164","oneMonthBeta":"0.2434"}]}
