{"bseNseJson":[{"etSymbol":"ratban","dateTime":"14:06 | 25-05-2021","listingFlag":true,"bestSellPrice":"206.60","symbol":"RBLBANK","preMarket":false,"trend":"equal","companyName":"RBLBANK","sectorRank":"23","openPrice":"211.95","industry":"Banks - Private Sector","instrument":"Equity","bestBuyQty":"145","companyName2":"RBL Bank Ltd.","seoName":"rbl-bank-ltd","companyRankYear":"2020","fiftyTwoWeekHighDateTime":"Jan  8 2021  4:00PM","fiftyTwoWeekHighPrice":"274.00","lowPrice":"205.90","segment":"BSE","highPrice":"211.95","scripCode":"540065","exchangeGroup":"A","sector":"Banks","lastTradedPrice":"206.35","value":"4.57","netChange":"-3.20","percentChange":"-1.53","displayDateTime":"2021-05-25 14:06:00","companyType":"equity","tpilCode":"13786","bestSellQty":"394","volume":"219629","companyId":"7750","groupName":"A ","fiftyTwoWeekLowDateTime":"May 26 2020  4:00PM","faceValue":"10.00","companyRank":"148","fiftyTwoWeekLowPrice":"108.25","nseScripCode":"RBLBANK","closePrice":"209.55","isSME":false,"bestBuyPrice":"206.45","isinCode":"INE976G01028"},{"etSymbol":"ratban","dateTime":"14:06 | 25-05-2021","listingFlag":true,"bestSellPrice":"206.55","symbol":"RBLBANK","preMarket":false,"trend":"equal","companyName":"RBLBANK","sectorRank":"24","openPrice":"211.50","industry":"Banks - Private Sector","instrument":"Equity","bestBuyQty":"747","companyName2":"RBL Bank Ltd.","seoName":"rbl-bank-ltd","companyRankYear":"2020","fiftyTwoWeekHighDateTime":"Jan  8 2021  3:59PM","fiftyTwoWeekHighPrice":"274.30","lowPrice":"205.75","segment":"NSE","highPrice":"211.75","scripCode":"540065","exchangeGroup":"OtherEQ","sector":"Banks","lastTradedPrice":"206.45","value":"139.21","netChange":"-3.55","percentChange":"-1.69","displayDateTime":"2021-05-25 14:06:00","companyType":"equity","tpilCode":"13786","bestSellQty":"6751","volume":"6683899","companyId":"7750","fiftyTwoWeekLowDateTime":"May 26 2020  3:59PM","faceValue":"10.00","wightedAverage":"208.28","companyRank":"148","fiftyTwoWeekLowPrice":"108.30","nseScripCode":"RBLBANKEQ","closePrice":"210.00","isSME":false,"bestBuyPrice":"206.45","isinCode":"INE976G01028"}],"companySD":[{"companyType":"equity","securitySubTypeId":"4","companyName":"RBL Bank Ltd.","exchangeId":"50","year3sd":"3.1927","companyId":"7750","year1sd":"5.0405","securityTypeId":"5","month1sd":"4.9813","modified":"2020-06-23 11:05:06.0","id":"8261","month6sd":"5.5480","month3sd":"5.5812"},{"companyType":"equity","securitySubTypeId":"4","companyName":"RBL Bank Ltd.","exchangeId":"47","year3sd":"3.1215","companyId":"7750","year1sd":"4.9267","securityTypeId":"5","month1sd":"3.8337","modified":"2020-06-23 11:05:06.0","id":"8260","month6sd":"5.3662","month3sd":"5.2156"}],"averageVolume":{"NSE":{"exchangeId":"50","companyid":"7750","fiveDaysAverage":"14273880.6000","tenDaysAverage":"13972206.2000","oneMonthAverage":"17073507.9000"},"BSE":{"exchangeId":"47","companyid":"7750","fiveDaysAverage":"1803158.4000","tenDaysAverage":"1315680.4000","oneMonthAverage":"996408.6333"}},"companyBeta":[{"exchangeId":"47","companyId":"7750","oneYearBeta":"1.4986","companyType":"equity","sixMonthBeta":"1.7512","companyName":"RBL Bank Ltd.","threeMonthBeta":"2.2933","dateModified":"2019-08-20 01:26:37.0","oneMonthBeta":"3.4559"},{"exchangeId":"50","companyId":"7750","oneYearBeta":"1.5008","companyType":"equity","sixMonthBeta":"1.7523","companyName":"RBL Bank Ltd.","threeMonthBeta":"2.2787","dateModified":"2019-08-20 01:26:38.0","oneMonthBeta":"3.4531"}]}
