{"chart":{"result":[{"meta":{"currency":"INR","symbol":"SKFINDIA.NS","exchangeName":"NSI","instrumentType":"EQUITY","firstTradeDate":1029123900,"regularMarketTime":1610430576,"gmtoffset":19800,"timezone":"IST","exchangeTimezoneName":"Asia/Kolkata","regularMarketPrice":1851.0,"chartPreviousClose":1856.9,"priceHint":2,"currentTradingPeriod":{"pre":{"timezone":"IST","start":1610423100,"end":1610423100,"gmtoffset":19800},"regular":{"timezone":"IST","start":1610423100,"end":1610445600,"gmtoffset":19800},"post":{"timezone":"IST","start":1610445600,"end":1610445600,"gmtoffset":19800}},"dataGranularity":"1d","range":"1d","validRanges":["1d","5d","1mo","3mo","6mo","1y","2y","5y","10y","ytd","max"]},"timestamp":[1610430576],"indicators":{"quote":[{"high":[1878.0],"close":[1851.0],"volume":[10871],"low":[1822.199951171875],"open":[1878.0]}],"adjclose":[{"adjclose":[1851.0]}]}}],"error":null}}