{"bseNseJson":[{"dateTime":"09:33 | 10-03-2021","etSymbol":"tast","bestSellPrice":"14864.45","listingFlag":true,"symbol":"TASTYBIT","preMarket":false,"trend":"equal","companyName":"Tasty Bite Eatables","openPrice":"14862.60","sectorRank":"19","industry":"FMCG Food & Beverages","instrument":"Equity","bestBuyQty":"1","companyName2":"Tasty Bite Eatables Ltd.","seoName":"tasty-bite-eatables-ltd","fiftyTwoWeekHighDateTime":"Feb 24 2021  5:30PM","companyRankYear":"2020","fiftyTwoWeekHighPrice":"16099.00","lowPrice":"14740.10","segment":"BSE","highPrice":"15200.00","scripCode":"519091","exchangeGroup":"A","sector":"FMCG","lastTradedPrice":"14800.00","value":"0.06","netChange":"-231.20","percentChange":"-1.54","displayDateTime":"2021-03-10 09:33:00","companyType":"equity","tpilCode":"4295","bestSellQty":"2","volume":"39","companyId":"12912","groupName":"A ","fiftyTwoWeekLowDateTime":"Mar 24 2020  4:00PM","faceValue":"10.00","companyRank":"NA","fiftyTwoWeekLowPrice":"7442.55","nseScripCode":"TASTYBITE","closePrice":"15031.20","isSME":false,"bestBuyPrice":"14800.00","isinCode":"INE488B01017"},{"dateTime":"09:33 | 10-03-2021","etSymbol":"tasbit","bestSellPrice":"14844.95","listingFlag":true,"symbol":"TASTYBITE","preMarket":false,"trend":"equal","companyName":"Tasty Bite Eatables","openPrice":"15010.00","sectorRank":"19","industry":"FMCG Food & Beverages","instrument":"Equity","bestBuyQty":"1","companyName2":"Tasty Bite Eatables Ltd.","seoName":"tasty-bite-eatables-ltd","fiftyTwoWeekHighDateTime":"Feb 24 2021  5:27PM","companyRankYear":"2020","fiftyTwoWeekHighPrice":"16124.90","lowPrice":"14618.75","segment":"NSE","highPrice":"15198.00","scripCode":"519091","exchangeGroup":"OtherEQ","sector":"FMCG","lastTradedPrice":"14852.50","value":"0.31","netChange":"-175.20","percentChange":"-1.17","displayDateTime":"2021-03-10 09:33:00","companyType":"equity","tpilCode":"4295","bestSellQty":"1","volume":"205","companyId":"12912","fiftyTwoWeekLowDateTime":"Mar 24 2020  3:41PM","faceValue":"10.00","wightedAverage":"14969.69","companyRank":"NA","fiftyTwoWeekLowPrice":"7456.95","nseScripCode":"TASTYBITEEQ","closePrice":"15027.70","isSME":false,"bestBuyPrice":"14807.75","isinCode":"INE488B01017"}],"companySD":[{"companyType":"equity","securitySubTypeId":"4","companyName":"Tasty Bite Eatables Ltd.","exchangeId":"50","year3sd":"2.7800","companyId":"12912","year1sd":"3.1623","securityTypeId":"5","month1sd":"1.7885","modified":"2020-06-23 11:06:38.0","id":"12396","month6sd":"3.8150","month3sd":"3.2651"},{"companyType":"equity","securitySubTypeId":"4","companyName":"Tasty Bite Eatables Ltd.","exchangeId":"47","year3sd":"2.9360","companyId":"12912","year1sd":"3.2594","securityTypeId":"5","month1sd":"1.8580","modified":"2020-06-23 11:06:38.0","id":"10135","month6sd":"4.0154","month3sd":"3.4405"}],"averageVolume":{"NSE":{"exchangeId":"50","companyid":"12912","fiveDaysAverage":"1614.8000","tenDaysAverage":"1692.2000","oneMonthAverage":"3134.8333"},"BSE":{"exchangeId":"47","companyid":"12912","fiveDaysAverage":"251.6000","tenDaysAverage":"287.9000","oneMonthAverage":"360.6000"}},"companyBeta":[{"exchangeId":"47","companyId":"12912","oneYearBeta":"0.6926","companyType":"equity","sixMonthBeta":"0.3172","companyName":"Tasty Bite Eatables Ltd.","threeMonthBeta":"0.1664","dateModified":"2019-08-20 01:30:26.0","threeYearBeta":"1.1563","oneMonthBeta":"0.7001"},{"exchangeId":"50","companyId":"12912","oneYearBeta":"0.5889","companyType":"equity","sixMonthBeta":"0.1280","companyName":"Tasty Bite Eatables Ltd.","threeMonthBeta":"0.0236","dateModified":"2019-08-20 01:30:26.0","oneMonthBeta":"0.3888"}]}
