{"bseNseJson":[{"etSymbol":"tcl","dateTime":"16:00 | 16-03-2021","listingFlag":true,"bestSellPrice":"0","symbol":"TATACOMM","preMarket":false,"trend":"equal","companyName":"Tata Communications","sectorRank":"3","openPrice":"1206.30","industry":"Telecommunications - Service","instrument":"Equity","bestBuyQty":"0","companyName2":"Tata Communications Ltd.","seoName":"tata-communications-ltd","companyRankYear":"2020","fiftyTwoWeekHighDateTime":"Mar  8 2021  4:00PM","fiftyTwoWeekHighPrice":"1365.00","lowPrice":"1202.00","segment":"BSE","highPrice":"1252.95","scripCode":"500483","exchangeGroup":"A","lastTradedPrice":"1213.00","sector":"Telecommunications","value":"26.94","netChange":"-84.30","percentChange":"-6.50","displayDateTime":"2021-03-16 16:00:00","companyType":"equity","tpilCode":"4646","bestSellQty":"0","volume":"219922","companyId":"11992","groupName":"A ","fiftyTwoWeekLowDateTime":"Mar 19 2020  4:00PM","faceValue":"10.00","companyRank":"96","nseScripCode":"TATACOMM","fiftyTwoWeekLowPrice":"205.70","closePrice":"1297.30","isSME":false,"bestBuyPrice":"0","isinCode":"INE151A01013"},{"etSymbol":"vidsan","dateTime":"16:00 | 16-03-2021","listingFlag":true,"bestSellPrice":"0","symbol":"TATACOMM","preMarket":false,"trend":"equal","companyName":"Tata Communications","sectorRank":"3","openPrice":"1210.00","industry":"Telecommunications - Service","instrument":"Equity","bestBuyQty":"0","companyName2":"Tata Communications Ltd.","seoName":"tata-communications-ltd","companyRankYear":"2020","fiftyTwoWeekHighDateTime":"Mar  8 2021  3:57PM","fiftyTwoWeekHighPrice":"1367.65","lowPrice":"1201.25","segment":"NSE","highPrice":"1252.90","scripCode":"500483","exchangeGroup":"OtherEQ","lastTradedPrice":"1214.80","sector":"Telecommunications","value":"1106.03","netChange":"-79.00","percentChange":"-6.11","displayDateTime":"2021-03-16 16:00:00","companyType":"equity","tpilCode":"4646","bestSellQty":"0","volume":"9021375","companyId":"11992","fiftyTwoWeekLowDateTime":"Mar 19 2020  3:56PM","faceValue":"10.00","wightedAverage":"1226.01","companyRank":"96","nseScripCode":"TATACOMMEQ","fiftyTwoWeekLowPrice":"200.00","closePrice":"1293.80","isSME":false,"bestBuyPrice":"0","isinCode":"INE151A01013"}],"companySD":[{"securitySubTypeId":"4","companyType":"equity","companyName":"Tata Communications Ltd.","year3sd":"2.7400","exchangeId":"50","companyId":"11992","year1sd":"4.0788","securityTypeId":"5","month1sd":"3.6138","modified":"2020-06-23 11:06:39.0","id":"9719","month6sd":"3.9737","month3sd":"4.3415"},{"securitySubTypeId":"4","companyType":"equity","companyName":"Tata Communications Ltd.","year3sd":"2.7572","exchangeId":"47","companyId":"11992","year1sd":"4.1346","securityTypeId":"5","month1sd":"3.9173","modified":"2020-06-23 11:06:39.0","id":"9718","month6sd":"4.0248","month3sd":"4.3858"}],"averageVolume":{"NSE":{"exchangeId":"50","companyid":"11992","fiveDaysAverage":"451462.0000","tenDaysAverage":"531116.9000","oneMonthAverage":"366055.5667"},"BSE":{"exchangeId":"47","companyid":"11992","fiveDaysAverage":"67073.0000","tenDaysAverage":"55810.8000","oneMonthAverage":"35190.0000"}},"companyBeta":[{"exchangeId":"47","oneYearBeta":"0.8223","companyId":"11992","companyType":"equity","sixMonthBeta":"0.6728","companyName":"Tata Communications Ltd.","threeMonthBeta":"0.8918","dateModified":"2019-08-20 01:30:27.0","threeYearBeta":"1.1035","oneMonthBeta":"1.0285"},{"exchangeId":"50","oneYearBeta":"0.8052","companyId":"11992","companyType":"equity","sixMonthBeta":"0.6765","companyName":"Tata Communications Ltd.","threeMonthBeta":"0.8999","dateModified":"2019-08-20 01:30:28.0","threeYearBeta":"1.0849","oneMonthBeta":"1.0880"}]}
